{
  "schema_version": "1.0.0",
  "record_type": "study",
  "id": "human-hsc-cdc42-casin-ex-vivo",
  "name": "Human aged HSC Cdc42 and CASIN ex vivo study",
  "summary": "Human donor HSC study comparing young and older hematopoietic stem and progenitor cells, including ex vivo CASIN treatment and xenotransplant readouts.",
  "study_type": "in_vitro",
  "status": "completed",
  "phase": "na",
  "population": "Human bone marrow or hematopoietic cell samples from young and older donors",
  "intervention_ids": [
    "casin"
  ],
  "hallmark_ids": [
    "stem_cell_exhaustion"
  ],
  "track_ids": [
    "stem-cell-rejuvenation"
  ],
  "endpoint_categories": [
    "biomarker",
    "mechanistic"
  ],
  "source_ids": [
    "pmid-33440922"
  ],
  "tags": [
    "human",
    "ex-vivo",
    "hsc",
    "cdc42"
  ]
}
