{
  "schema_version": "1.0.0",
  "record_type": "source",
  "id": "pmid-32686219",
  "name": "Senolytic drugs: from discovery to translation",
  "short_name": "Senolytic drugs translation review",
  "summary": "2020 Journal of Internal Medicine review summarizing senolytic discovery, intermittent hit-and-run rationale, broad preclinical disease coverage, early pilot signals, active clinical trial areas, and the caution that senolytics should not be used outside clinical trials until those studies are done.",
  "source_type": "review",
  "authors": [
    "Kirkland JL",
    "Tchkonia T"
  ],
  "venue": "Journal of Internal Medicine",
  "year": 2020,
  "published_on": "2020-08-04",
  "doi": "10.1111/joim.13141",
  "pmid": "32686219",
  "urls": [
    "https://pubmed.ncbi.nlm.nih.gov/32686219/",
    "https://doi.org/10.1111/joim.13141"
  ],
  "tags": [
    "senolytics",
    "review",
    "translation",
    "safety",
    "trial-boundary",
    "coverage-repair"
  ]
}
