{
  "schema_version": "1.0.0",
  "record_type": "source",
  "id": "doi-10.3389-fragi.2026.1732426",
  "name": "Multimodal longevity protocol with autologous pro-regenerative conditioned media",
  "short_name": "APRC-CM multimodal longevity pilot",
  "summary": "A Frontiers in Aging accepted article reporting a single-arm open-label healthy-adult pilot that combined lifestyle optimization, supplements, and two intravenous infusions of autologous pro-regenerative cell-derived conditioned media.",
  "created_at": "2026-06-15T10:05:00Z",
  "updated_at": "2026-06-15T10:05:00Z",
  "tags": [
    "extracellular-vesicle-and-secretome-therapies",
    "conditioned-media",
    "secretome",
    "healthy-aging",
    "biological-age"
  ],
  "source_type": "journal_article",
  "authors": [
    "Sottas PE",
    "Ortega E",
    "Addor G",
    "Bhatia S",
    "Lewinsohn M"
  ],
  "venue": "Frontiers in Aging",
  "year": 2026,
  "published_on": "2026-06-09",
  "doi": "10.3389/fragi.2026.1732426",
  "registry_ids": [
    "NCT07322224"
  ],
  "urls": [
    "https://www.frontiersin.org/journals/aging/articles/10.3389/fragi.2026.1732426/abstract",
    "https://doi.org/10.3389/fragi.2026.1732426",
    "https://clinicaltrials.gov/study/NCT07322224"
  ]
}
