{
  "schema_version": "1.0.0",
  "record_type": "source",
  "id": "nct-05054894",
  "name": "Plasmapheresis for Treatment of Age-Related Frailty",
  "short_name": "Age-related frailty TPE registry",
  "summary": "ClinicalTrials.gov early phase 1 single-group age-related frailty plasmapheresis registry, unknown status with estimated 2025 completion and no posted results in the June 9, 2026 API view.",
  "source_type": "trial_registry",
  "authors": [
    "ClinicalTrials.gov"
  ],
  "venue": "ClinicalTrials.gov",
  "year": 2021,
  "published_on": "2021-09-23",
  "registry_ids": [
    "NCT05054894"
  ],
  "urls": [
    "https://clinicaltrials.gov/study/NCT05054894"
  ],
  "tags": [
    "circulating-factor-modulation",
    "therapeutic-plasma-exchange",
    "frailty",
    "human-function",
    "no-results",
    "coverage-repair"
  ]
}
