{
  "schema_version": "1.0.0",
  "record_type": "study",
  "id": "bgp15-insulin-resistance-proof-of-concept",
  "name": "BGP-15 insulin resistance proof-of-concept trial",
  "summary": "A 28-day randomized, double-blind, placebo-controlled proof-of-concept trial of BGP-15 in nondiabetic insulin-resistant patients.",
  "study_type": "interventional",
  "status": "completed",
  "phase": "pilot",
  "population": "Nondiabetic patients with impaired glucose tolerance and insulin resistance",
  "sample_size": 47,
  "intervention_ids": [
    "bgp-15"
  ],
  "hallmark_ids": [
    "loss_of_proteostasis"
  ],
  "track_ids": [
    "chaperone-and-heat-shock-support"
  ],
  "endpoint_categories": [
    "biomarker",
    "safety"
  ],
  "source_ids": [
    "pmid-19214941"
  ],
  "tags": [
    "human",
    "randomized",
    "bgp-15",
    "biomarker"
  ]
}
