{
  "schema_version": "1.0.0",
  "record_type": "study",
  "id": "metformin-aerobic-exercise-older-adults",
  "name": "Metformin during aerobic exercise training in older adults",
  "summary": "A double-blind randomized older-adult trial testing metformin or placebo during 12 weeks of aerobic exercise training, with insulin sensitivity, VO2 max, glucose, and skeletal-muscle mitochondrial respiration endpoints.",
  "study_type": "interventional",
  "status": "completed",
  "phase": "pilot",
  "population": "Older adults around 62 years of age undergoing aerobic exercise training",
  "sample_size": 53,
  "intervention_ids": [
    "metformin"
  ],
  "hallmark_ids": [
    "deregulated_nutrient_sensing"
  ],
  "track_ids": [
    "ampk-and-metabolic-modulators"
  ],
  "endpoint_categories": [
    "functional",
    "biomarker",
    "mechanistic"
  ],
  "source_ids": [
    "pmid-30548390"
  ],
  "tags": [
    "human",
    "metformin",
    "exercise",
    "mitochondria"
  ]
}
