{
  "schema_version": "1.0.0",
  "record_type": "source",
  "id": "nct-04998357",
  "name": "Autologous Mitochondrial Transplant for Cerebral Ischemia",
  "short_name": "Autologous mitochondrial transplant cerebral ischemia registry",
  "summary": "ClinicalTrials.gov registry record for a recruiting University of Washington study of endovascular autologous mitochondrial transplantation during standard-of-care reperfusion therapy for cerebral ischemia; status and dates are recorded as of June 3, 2026, with last update posted May 21, 2025 and no registry-posted results.",
  "source_type": "trial_registry",
  "authors": [
    "University of Washington"
  ],
  "venue": "ClinicalTrials.gov",
  "year": 2021,
  "published_on": "2021-08-10",
  "registry_ids": [
    "NCT04998357"
  ],
  "urls": [
    "https://clinicaltrials.gov/study/NCT04998357"
  ],
  "tags": [
    "mitochondrial-delivery-and-transplantation",
    "autologous-mitochondrial-transplantation",
    "trial-registry",
    "stroke",
    "safety"
  ]
}
